odoo/addons/account_payment_order_sequence_payment_mode/README.rst
odoo/addons/account_payment_order_sequence_payment_mode/__init__.py
odoo/addons/account_payment_order_sequence_payment_mode/__manifest__.py
odoo/addons/account_payment_order_sequence_payment_mode/i18n/account_payment_order_sequence_payment_mode.pot
odoo/addons/account_payment_order_sequence_payment_mode/i18n/ca.po
odoo/addons/account_payment_order_sequence_payment_mode/i18n/es.po
odoo/addons/account_payment_order_sequence_payment_mode/i18n/it.po
odoo/addons/account_payment_order_sequence_payment_mode/models/__init__.py
odoo/addons/account_payment_order_sequence_payment_mode/models/account_payment_mode.py
odoo/addons/account_payment_order_sequence_payment_mode/models/account_payment_order.py
odoo/addons/account_payment_order_sequence_payment_mode/readme/CONTRIBUTORS.rst
odoo/addons/account_payment_order_sequence_payment_mode/readme/DESCRIPTION.rst
odoo/addons/account_payment_order_sequence_payment_mode/readme/USAGE.rst
odoo/addons/account_payment_order_sequence_payment_mode/static/description/icon.png
odoo/addons/account_payment_order_sequence_payment_mode/static/description/index.html
odoo/addons/account_payment_order_sequence_payment_mode/views/account_payment_mode.xml
odoo14_addon_account_payment_order_sequence_payment_mode-14.0.1.0.1.dev12.dist-info/METADATA
odoo14_addon_account_payment_order_sequence_payment_mode-14.0.1.0.1.dev12.dist-info/WHEEL
odoo14_addon_account_payment_order_sequence_payment_mode-14.0.1.0.1.dev12.dist-info/top_level.txt
odoo14_addon_account_payment_order_sequence_payment_mode-14.0.1.0.1.dev12.dist-info/RECORD
